mp3chaps.py
mp3chapters-0.5.2.dist-info/LICENSE.txt
mp3chapters-0.5.2.dist-info/METADATA
mp3chapters-0.5.2.dist-info/WHEEL
mp3chapters-0.5.2.dist-info/entry_points.txt
mp3chapters-0.5.2.dist-info/top_level.txt
mp3chapters-0.5.2.dist-info/RECORD
