Metadata-Version: 2.1
Name: mp3chapters
Version: 0.5.2
Summary: tool for inserting chapter marks in mp3 files
Home-page: https://github.com/rfjaquez/mp3chapters
Author: rfjaquez
Author-email: rfjqz-github@yahoo.com
License: MIT
Keywords: mp3 chapters
Classifier: Development Status :: 3 - Alpha
Classifier: Environment :: Console
Classifier: License :: OSI Approved :: MIT License
Classifier: Programming Language :: Python :: 3
Classifier: Topic :: Multimedia :: Sound/Audio
License-File: LICENSE.txt
Requires-Dist: docopt (>=0.6.2)
Requires-Dist: eyeD3 (>=0.9.6)
